regarding/__about__.py
regarding/__init__.py
regarding/__main__.py
regarding/about.py
regarding/meta.py
regarding-0.2.0.dist-info/licenses/AUTHORS
regarding-0.2.0.dist-info/licenses/LICENSE
regarding-0.2.0.dist-info/METADATA
regarding-0.2.0.dist-info/WHEEL
regarding-0.2.0.dist-info/entry_points.txt
regarding-0.2.0.dist-info/top_level.txt
regarding-0.2.0.dist-info/RECORD
